README.md
setup.py
ytutils/Channel.py
ytutils/Video.py
ytutils/__init__.py
ytutils.egg-info/PKG-INFO
ytutils.egg-info/SOURCES.txt
ytutils.egg-info/dependency_links.txt
ytutils.egg-info/top_level.txt