Metadata-Version: 2.1
Name: ytutils
Version: 0.1.0.4
Summary: YouTube Extractor
Home-page: https://github.com/SanjayDevTech/ytutils
Author: Sanjay Developer
Author-email: sureshsanjay805@gmail.com
License: MIT
Keywords: youtube,youtube video,youtube channel
Platform: UNKNOWN
Classifier: Development Status :: 4 - Beta
Classifier: Intended Audience :: Developers
Classifier: Topic :: Software Development :: Build Tools
Classifier: License :: OSI Approved :: MIT License
Classifier: Programming Language :: Python :: 3
Classifier: Programming Language :: Python :: 3.4
Classifier: Programming Language :: Python :: 3.5
Classifier: Programming Language :: Python :: 3.6
